setup.py
txsockjs_client/__init__.py
txsockjs_client.egg-info/PKG-INFO
txsockjs_client.egg-info/SOURCES.txt
txsockjs_client.egg-info/dependency_links.txt
txsockjs_client.egg-info/not-zip-safe
txsockjs_client.egg-info/requires.txt
txsockjs_client.egg-info/top_level.txt