Metadata-Version: 1.1
Name: txsockjs-client
Version: 0.1.0
Summary: SockJS client for Twisted-Python
Home-page: http://github.com/cravler/sockjs-client-twisted/
Author: Sergei Vizel
Author-email: sergei.vizel@gmail.com
License: MIT
Platform: any
Classifier: Framework :: Twisted
Classifier: Intended Audience :: Developers
Classifier: License :: OSI Approved :: MIT License
Classifier: Operating System :: OS Independent
Classifier: Programming Language :: Python
Classifier: Topic :: Internet
